quant_indicators/__init__.py
quant_indicators/quant_indicators.py
quant_indicators-1.1.dist-info/METADATA
quant_indicators-1.1.dist-info/WHEEL
quant_indicators-1.1.dist-info/top_level.txt
quant_indicators-1.1.dist-info/RECORD
