Metadata-Version: 2.1
Name: quant-indicators
Version: 1.1
Summary: A simple indicator library for stock tickers
Author: NgocAn
Author-email: anlam9614@gmail.com
Classifier: Programming Language :: Python :: 3
Classifier: License :: OSI Approved :: MIT License
Classifier: Operating System :: OS Independent
Requires-Python: >=3.6
Requires-Dist: requests
Requires-Dist: pandas
Requires-Dist: numpy
